xmldiff/__init__.py
xmldiff/actions.py
xmldiff/diff.py
xmldiff/diff_match_patch.py
xmldiff/formatting.py
xmldiff/main.py
xmldiff/patch.py
xmldiff/utils.py
xmldiff-2.7.0.dist-info/LICENSE.txt
xmldiff-2.7.0.dist-info/METADATA
xmldiff-2.7.0.dist-info/WHEEL
xmldiff-2.7.0.dist-info/entry_points.txt
xmldiff-2.7.0.dist-info/top_level.txt
xmldiff-2.7.0.dist-info/zip-safe
xmldiff-2.7.0.dist-info/RECORD
