Metadata-Version: 2.1
Name: xmldiff
Version: 2.7.0
Summary: Creates diffs of XML files
Home-page: https://github.com/Shoobx/xmldiff
Author: Lennart Regebro
Author-email: lregebro@shoobx.com
License: MIT
Project-URL: Source Code, https://github.com/Shoobx/xmldiff
Keywords: xml,html,diff
Classifier: Development Status :: 4 - Beta
Classifier: Intended Audience :: Developers
Classifier: Intended Audience :: End Users/Desktop
Classifier: Topic :: Text Processing :: Markup :: XML
Classifier: License :: OSI Approved :: MIT License
Classifier: Operating System :: OS Independent
Classifier: Programming Language :: Python
Classifier: Programming Language :: Python :: 3
Classifier: Programming Language :: Python :: 3.8
Classifier: Programming Language :: Python :: 3.9
Classifier: Programming Language :: Python :: 3.10
Classifier: Programming Language :: Python :: 3.11
Classifier: Programming Language :: Python :: 3.12
Classifier: Programming Language :: Python :: 3 :: Only
Classifier: Programming Language :: Python :: Implementation :: PyPy
Requires-Python: >=3.8
License-File: LICENSE.txt
Requires-Dist: setuptools
Requires-Dist: lxml (>=3.1.0)
Provides-Extra: devenv
Requires-Dist: black ; extra == 'devenv'
Requires-Dist: coverage ; extra == 'devenv'
Requires-Dist: flake8 ; extra == 'devenv'
Requires-Dist: zest.releaser[recommended] ; extra == 'devenv'
